recent_earthquake2/__init__.py
latterearthquake_indonesia-0.1.2.dist-info/LICENSE
latterearthquake_indonesia-0.1.2.dist-info/METADATA
latterearthquake_indonesia-0.1.2.dist-info/WHEEL
latterearthquake_indonesia-0.1.2.dist-info/top_level.txt
latterearthquake_indonesia-0.1.2.dist-info/RECORD
