Metadata-Version: 2.1
Name: latterearthquake-indonesia
Version: 0.1.2
Summary: This package will get recent earthquake detected fromMeteorological, Climatology and Geophysics Agency of Indonesia's website
Home-page: https://github.com/Glaceon-Training/recent-indonesia-earthquake
Author: Ryandri
Author-email: radhinusa@gmail.com
Classifier: Programming Language :: Python :: 3
Classifier: License :: OSI Approved :: GNU General Public License v3 (GPLv3)
Classifier: Operating System :: OS Independent
Classifier: Development Status :: 4 - Beta
Requires-Python: >=3.6
License-File: LICENSE
